{
  "wallet": {
    "usdc": "77.33",
    "eth": "0.00",
    "botcoin": "2.29M"
  },
  "status": "EXECUTING $10 BET",
  "lastBet": {
    "market": "BTC 12:30-12:45 PM ET (UP)",
    "result": "LIVE - SIGNING",
    "pnl": "Pending"
  },
  "mining": {
    "credits": "DISABLED",
    "epoch": "N/A",
    "hurdle": "DELETED"
  },
  "aiSignal": {
    "strategist": "Ensemble Update: RSI 12.94 is extreme oversold. 100% conviction on UP bounce. Execution priority: MAX.",
    "dataWorker": "Bankr Job M5MAHD... active. Routing via Proxy 0x707C for visibility."
  },
  "lastUpdate": "Sunday, Feb 22, 17:41 GMT"
}